machinelite/__init__.py
machinelite/multivariate/__init__.py
machinelite/multivariate/classification.py
machinelite/multivariate/classification_grid.py
machinelite/multivariate/regression.py
machinelite/multivariate/regression_grid.py
machinelite/univariate/__init__.py
machinelite/univariate/classification.py
machinelite/univariate/classification_grid.py
machinelite/univariate/regression.py
machinelite/univariate/regression_grid.py
machinelite-0.0.2.dist-info/LICENSE
machinelite-0.0.2.dist-info/METADATA
machinelite-0.0.2.dist-info/WHEEL
machinelite-0.0.2.dist-info/top_level.txt
machinelite-0.0.2.dist-info/RECORD
