Metadata-Version: 2.1
Name: machinelite
Version: 0.0.2
Summary: Sci-Lite is Light version of Supervised Machine Learning Model
Home-page: https://github.com/AyushJainSparsh/MachineLite.git
Author: Ayush Jain Sparsh
Author-email: ayushjainsparsh2004.ajs@gmail.com
Classifier: Programming Language :: Python :: 3
Classifier: License :: OSI Approved :: MIT License
Classifier: Operating System :: OS Independent
Requires-Python: >=3.6
License-File: LICENSE
Requires-Dist: pandas
Requires-Dist: scikit-learn
Requires-Dist: catboost
